{
  "screenGroups": [
    {
      "groupId": "PDG001",
      "groupName": "PD"
    },
    {
      "groupId": "CLG002",
      "groupName": "Vehicle Details"
    },
    {
      "groupId": "APG008",
      "groupName": "Applicant Details"
    }
  ],
  "screenIds": [
    {
      "id": "PDS001",
      "name": "PD-Personal Details - Maker",
      "groupId": "PDG001"
    },
    {
      "id": "PDS002",
      "groupId": "PDG001",
      "name": "PD-Income Details - Maker"
    },
    {
      "id": "PDS003",
      "groupId": "PDG001",
      "name": "PD-Loan Details - Maker"
    },
    {
      "id": "PDS004",
      "groupId": "PDG001",
      "name": "PD-Reference Details - Maker"
    },
    {
      "id": "PDS005",
      "name": "PD-Personal Details  - Checker",
      "groupId": "PDG001"
    },
    {
      "id": "PDS006",
      "groupId": "PDG001",
      "name": "PD-Income Details  - Checker"
    },
    {
      "id": "PDS007",
      "groupId": "PDG001",
      "name": "PD-Loan Details   - Checker"
    },
    {
      "id": "PDS008",
      "groupId": "PDG001",
      "name": "PD-Reference Details   - Checker"
    },
    {
      "id": "CLS002",
      "groupId": "CLG002",
      "name": "Vehicle Details - QDE"
    },
    {
      "id": "CLS004",
      "groupId": "CLG002",
      "name": "Vehicle Details - ADE"
    },
    {
      "id": "CLS006",
      "groupId": "CLG002",
      "name": "Vehicle Details - DDE"
    },
    {
      "id": "APS011",
      "groupId": "APG008",
      "name": "Apllicant Basic Details - ADE"
    },
    {
      "id": "TVS001",
      "groupId": "TVG001",
      "name": "Tele-Verfication-form"
    },
    {
      "id": "APS018",
      "groupId": "APG010",
      "name": "Tele-Verfication-form"
    }
  ],
  "udfFields": [
    {
      "id": "firstName",
      "label": "First Name",
      "placeholder": "First Name",
      "mandatory": true,
      "contorlType": "textbox",
      "inputType": "alpha",
      "maxLength": {
        "rule": 30,
        "msg": ""
      },
      "pattenCheck": {
        "rule": "",
        "msg": ""
      }
    },
    {
      "id": "middleName",
      "label": "Middle Name",
      "placeholder": "Middle Name",
      "mandatory": false,
      "contorlType": "textbox",
      "inputType": "alpha",
      "maxLength": {
        "rule": 30,
        "msg": ""
      }
    },
    {
      "id": "lastName",
      "label": "Last Name",
      "placeholder": "Last Name",
      "mandatory": true,
      "contorlType": "textbox",
      "inputType": "alpha",
      "maxLength": {
        "rule": 30,
        "msg": ""
      }
    },
    {
      "id": "applicantName",
      "label": "Full Name",
      "placeholder": "Full Name",
      "mandatory": false,
      "contorlType": "textbox",
      "inputType": "alpha",
      "maxLength": {
        "rule": 30,
        "msg": ""
      }
    },
    {
      "id": "fatherFirstName",
      "label": "Father First Name",
      "placeholder": "Father First Name",
      "mandatory": true,
      "contorlType": "textbox",
      "inputType": "alpha",
      "maxLength": {
        "rule": 30,
        "msg": ""
      }
    },
    {
      "id": "fatherMiddleName",
      "label": "Father Middle Name",
      "placeholder": "Father Middle Name",
      "mandatory": false,
      "contorlType": "textbox",
      "inputType": "alpha",
      "maxLength": {
        "rule": 30,
        "msg": ""
      }
    },
    {
      "id": "fatherLastName",
      "label": "Father Last Name",
      "placeholder": "Father Last Name",
      "mandatory": false,
      "contorlType": "textbox",
      "inputType": "alpha",
      "maxLength": {
        "rule": 30,
        "msg": ""
      }
    },
    {
      "id": "fatherFullName",
      "label": "Father Full Name",
      "placeholder": "Father Full Name",
      "mandatory": false,
      "contorlType": "textbox",
      "inputType": "alpha",
      "maxLength": {
        "rule": 30,
        "msg": ""
      }
    },
    {
      "id": "gender",
      "label": "Gender",
      "placeholder": "Gender Name",
      "mandatory": true,
      "contorlType": "selectbox",
      "values": "gender"
    },
    {
      "id": "dob",
      "label": "Date of Birth",
      "placeholder": "Date of Birth",
      "mandatory": true,
      "contorlType": "date"
    },
    {
      "id": "maritalStatus",
      "label": "Marital Status",
      "placeholder": "Marital Status",
      "mandatory": true,
      "contorlType": "selectbox",
      "values": "maritalStatus"
    },
    {
      "id": "weddingAnniversaryDate",
      "label": "Wedding Anniversary Date",
      "placeholder": "Wedding Anniversary Date",
      "mandatory": false,
      "contorlType": "date"
    },
    {},
    {
      "id": "physicallyChallenged",
      "label": "Physically Challenged",
      "placeholder": "Physically Challenged",
      "mandatory": false,
      "contorlType": "selectbox",
      "values": [
        {
          "key": 1,
          "value": "Yes"
        },
        {
          "key": 2,
          "value": "No"
        }
      ]
    },
    {
      "id": "customerProfile",
      "label": "Customer Profile",
      "placeholder": "Customer Profile",
      "mandatory": false,
      "contorlType": "selectbox",
      "values": [
        {
          "key": 1,
          "value": "FTU"
        },
        {
          "key": 2,
          "value": "FTB"
        }
      ]
    },
    {
      "id": "priorInfo",
      "label": "Prior Info",
      "placeholder": "Prior Info",
      "mandatory": false,
      "contorlType": "selectbox",
      "values": [
        {
          "key": 1,
          "value": "Driver cum owner"
        },
        {
          "key": 2,
          "value": "With Agricultural land"
        },
        {
          "key": 3,
          "value": "With house property"
        },
        {
          "key": 4,
          "value": "Without repayment track record"
        },
        {
          "key": 5,
          "value": "With proven repayment track record"
        }
      ]
    },
    {
      "id": "exShowRoomCost",
      "label": "Ex ShowRoom Cost",
      "placeholder": "Ex ShowRoom Cost",
      "mandatory": true,
      "contorlType": "textbox",
      "inputType": "number",
      "maxLength": {
        "rule": 12,
        "msg": ""
      },
      "pattenCheck": {
        "rule": "",
        "msg": ""
      }
    },
    {
      "id": "region",
      "label": "Region",
      "placeholder": "Region",
      "mandatory": true,
      "contorlType": "selectbox",
      "values": "assetRegion"
    },
    {
      "id": "noOfVehicles",
      "label": "No Of Vehicles",
      "placeholder": "No Of Vehicles",
      "mandatory": false,
      "contorlType": "textbox",
      "inputType": "number",
      "maxLength": {
        "rule": 3,
        "msg": ""
      },
      "pattenCheck": {
        "rule": "",
        "msg": ""
      }
    },
    {
      "id": "finalAssetCost",
      "label": "Final Asset Cost",
      "placeholder": "Final Asset Cost",
      "mandatory": false,
      "contorlType": "textbox",
      "inputType": "number",
      "maxLength": {
        "rule": 12,
        "msg": ""
      }
    },
    {
      "id": "rcOwnerName",
      "label": "Vehicle Owner Name",
      "placeholder": "Vehicle Owner Name",
      "mandatory": true,
      "contorlType": "textbox",
      "inputType": "alpha",
      "maxLength": {
        "rule": 30,
        "msg": ""
      },
      "pattenCheck": {
        "rule": "",
        "msg": ""
      }
    },
    {
      "id": "address",
      "label": "Vehicle Address",
      "placeholder": "Vehicle Address",
      "mandatory": true,
      "contorlType": "textarea"
    },
    {
      "id": "fsrdFundingReq",
      "label": "FRSD Funding Required",
      "placeholder": "FRSD Funding Required",
      "mandatory": false,
      "contorlType": "checkbox"
    },
    {
      "id": "vas",
      "label": "VAS",
      "placeholder": "VAS",
      "mandatory": false,
      "value": "1",
      "contorlType": "radio"
    },
    {
      "id": "rationCard",
      "label": "Ration Card Number",
      "placeholder": "Ration Card Number",
      "mandatory": true,
      "contorlType": "textbox",
      "inputType": "alpha-numeric",
      "maxLength": {
        "rule": 30,
        "msg": ""
      },
      "pattenCheck": {
        "rule": "",
        "msg": ""
      }
    },
    {
      "id": "employeeName",
      "label": "Employee Name",
      "placeholder": "Employee Name",
      "mandatory": true,
      "contorlType": "textbox",
      "inputType": "alpha",
      "maxLength": {
        "rule": 30,
        "msg": ""
      },
      "pattenCheck": {
        "rule": "",
        "msg": ""
      }
    },
    {
      "id": "employeeIncome",
      "label": "Employee Income",
      "placeholder": "Employee Income",
      "mandatory": true,
      "contorlType": "textbox",
      "inputType": "number",
      "maxLength": {
        "rule": 12,
        "msg": ""
      },
      "pattenCheck": {
        "rule": "",
        "msg": ""
      }
    },
    {
      "id": "bankName",
      "label": "Bank Name",
      "placeholder": "Bank Name",
      "mandatory": true,
      "contorlType": "textbox",
      "inputType": "alpha",
      "maxLength": {
        "rule": 30,
        "msg": ""
      },
      "pattenCheck": {
        "rule": "",
        "msg": ""
      }
    },
    {
      "id": "bankRemarks",
      "label": "Remarks",
      "placeholder": "",
      "mandatory": true,
      "contorlType": "textarea"
    },
    {
      "id": "activityName",
      "label": "Owner Name",
      "placeholder": "Name",
      "mandatory": true,
      "contorlType": "textbox",
      "inputType": "alpha",
      "maxLength": {
        "rule": 30,
        "msg": ""
      },
      "pattenCheck": {
        "rule": "",
        "msg": ""
      }
    },
    {
      "id": "isFarmer",
      "label": "Are You Farmer",
      "placeholder": "FRSD Funding Required",
      "mandatory": false,
      "contorlType": "checkbox"
    },
    {
      "id": "insuranceNumebr",
      "label": "Insurance Number",
      "placeholder": "Insurance Number",
      "mandatory": true,
      "contorlType": "textbox",
      "inputType": "number",
      "maxLength": {
        "rule": 15,
        "msg": ""
      },
      "pattenCheck": {
        "rule": "",
        "msg": ""
      }
    }
  ],
  "screenUdfMapping": {
    "PDS001": {
      "layout": 3,
      "fields": [
        {
          "name": "firstName",
          "show": true,
          "disable": false
        },
        {
          "name": "middleName",
          "show": true,
          "disable": false
        },
        {
          "name": "lastName",
          "show": true,
          "disable": false
        },
        {
          "name": "applicantName",
          "show": true,
          "disable": false
        },
        {
          "name": "fatherFirstName",
          "show": true,
          "disable": false
        },
        {
          "name": "fatherMiddleName",
          "show": true,
          "disable": false
        },
        {
          "name": "fatherLastName",
          "show": true,
          "disable": false
        },
        {
          "name": "fatherFullName",
          "show": true,
          "disable": false
        },
        {
          "name": "gender",
          "show": true,
          "disable": false
        },
        {
          "name": "maritalStatus",
          "show": true,
          "disable": false
        },
        {
          "name": "religion",
          "show": true,
          "disable": false
        },
        {
          "name": "category",
          "show": true,
          "disable": false
        },
        {
          "name": "physicallyChallenged",
          "show": true,
          "disable": false
        },
        {
          "name": "customerProfile",
          "show": true,
          "disable": false
        },
        {
          "name": "priorInfo",
          "show": true,
          "disable": false
        },
        {
          "name": "businessKey",
          "show": true,
          "disable": false
        },
        {
          "name": "occupationType",
          "show": true,
          "disable": false
        },
        {
          "name": "businessType",
          "show": true,
          "disable": false
        },
        {
          "name": "vehicleApplication",
          "show": true,
          "disable": false
        },
        {
          "name": "educationalBackgroundType",
          "show": true,
          "disable": false
        },
        {
          "name": "isMinority",
          "show": true,
          "disable": false
        },
        {
          "name": "community",
          "show": true,
          "disable": false
        },
        {
          "name": "srto",
          "show": true,
          "disable": false
        },
        {
          "name": "contactNo",
          "show": true,
          "disable": false
        },
        {
          "name": "alternateContactNo",
          "show": true,
          "disable": false
        },
        {
          "name": "email",
          "show": true,
          "disable": false
        },
        {
          "name": "residentStatus",
          "show": true,
          "disable": false
        },
        {
          "name": "accomodationType",
          "show": true,
          "disable": false
        },
        {
          "name": "noOfYears",
          "show": true,
          "disable": false
        },
        {
          "name": "noOfMonths",
          "show": true,
          "disable": false
        },
        {
          "name": "noOfYearsResidingInCurrResidence",
          "show": true,
          "disable": false
        },
        {
          "name": "noOfAdultDependant",
          "show": true,
          "disable": false
        },
        {
          "name": "noOfChildrenDependant",
          "show": true,
          "disable": false
        },
        {
          "name": "residentialLocality",
          "show": true,
          "disable": false
        },
        {
          "name": "houseOwnership",
          "show": true,
          "disable": false
        },
        {
          "name": "areaOfProperty",
          "show": true,
          "disable": false
        },
        {
          "name": "propertyValue",
          "show": true,
          "disable": false
        },
        {
          "name": "bankAccHolderName",
          "show": true,
          "disable": false
        },
        {
          "name": "cibilScore",
          "show": true,
          "disable": false
        }
      ]
    },
    "CLS002": {
      "layout": 3,
      "fields": [
        {
          "name": "region",
          "show": true,
          "disable": false
        },
        {
          "name": "noOfVehicles",
          "show": true,
          "disable": false
        },
        {
          "name": "exShowRoomCost",
          "show": true,
          "disable": false
        }
      ]
    },
    "CLS004": {
      "layout": 3,
      "fields": [
        {
          "name": "region",
          "show": true,
          "disable": false
        },
        {
          "name": "noOfVehicles",
          "show": true,
          "disable": false
        },
        {
          "name": "exShowRoomCost",
          "show": true,
          "disable": false
        },
        {
          "name": "address",
          "show": true,
          "disable": false
        },
        {
          "name": "vas",
          "show": true,
          "disable": false
        }
      ]
    },
    "CLS006": {
      "layout": 3,
      "fields": [
        {
          "name": "region",
          "show": true,
          "disable": false
        },
        {
          "name": "noOfVehicles",
          "show": true,
          "disable": false
        },
        {
          "name": "exShowRoomCost",
          "show": true,
          "disable": false
        },
        {
          "name": "finalAssetCost",
          "show": true,
          "disable": false
        },
        {
          "name": "rcOwnerName",
          "show": true,
          "disable": false
        },
        {
          "name": "fsrdFundingReq",
          "show": true,
          "disable": false
        }
      ]
    },
    "APS011": {
      "layout": 3,
      "fields":[
        {
            "name": "rationCard",
            "show": true,
            "disable": false
        }
      ]
    },
    "TVS001": {
      "layout": 3,
      "fields": [
        {
          "name": "employeeName",
            "show": true,
            "disable": false
        },
        {
          "name": "employeeIncome",
            "show": true,
            "disable": false 
        }
      ]
    },
    "APS018": {
      "layout": 3,
      "fields": [
        {
          "name": "bankName",
            "show": true,
            "disable": false
        },
        {
          "name": "bankRemarks",
            "show": true,
            "disable": false 
        }
      ]
    },
    "PSS001": {
      "layout": 3,
      "fields": [
        {
          "name": "activityName",
          "show": true,
          "disable": false
        },
        {
          "name": "isFarmer",
          "show": true,
          "disable": false
        }
      ]
    },
    "ISS001": {
      "layout": 3,
      "fields": [
        {
          "name": "insuranceNumebr",
          "show": true,
          "disable": false
        }
      ]
    }
  }
}